[
    {
      "cmd": "AT",
      "description": "Test if the module is responding."
    },
    {
      "cmd": "AT+GMR",
      "description": "Check Version Information."
    },
    {
      "cmd": "AT+GMI",
      "description": "Determine the identity of the modem manufacturer."
    },
    {
      "cmd": "AT+GMM",
      "description": "Get the modem model."
    },
    {
      "cmd": "AT+CGMR",
      "description": "Get firmware version."
    },
    {
      "cmd": "AT+CGSN",
      "description": "Get the International Mobile station Equipment Identity (IMEI)."
    },
    {
      "cmd": "AT+RST",
      "description": "Restart the module."
    },
    {
      "cmd": "AT+CMD",
      "description": "All supported AT commands."
    },
    {
      "cmd": "AT+CWMODE=1",
      "description": "Set WiFi mode to Station."
    },
    {
      "cmd": "ATE0",
      "description": "Switch echo off."
    },
    {
      "cmd": "ATE1",
      "description": "Switch echo on."
    },
    {
      "cmd": "AT+RESTORE",
      "description": "Restore factory default settings of the module."
    }
  ]
  